dautil/__init__.py
dautil/date_time.py
dautil/pandas_display.py
dautil/pandas_util.py
dautil/parser.py
dautil/path_util.py
dautil/plot.py
dautil/scrape_web.py
dautil/stat.py
dautil/string.py
dautil/sym.py
dautil/util.py
dautil/IO/__init__.py
dautil/IO/h5.py
dautil/IO/pandas.py
dautil/IO/sacct.py
dautil/IO/stdio.py
dautil/IO/timeit_IO.py
dautil/script/__init__.py
dautil/script/detect_missing_track_type.py
dautil/script/glom_yaml.py
dautil/script/tree_html_at_level.py
dautilpy-0.2.0.dist-info/LICENSE
dautilpy-0.2.0.dist-info/METADATA
dautilpy-0.2.0.dist-info/WHEEL
dautilpy-0.2.0.dist-info/entry_points.txt
dautilpy-0.2.0.dist-info/top_level.txt
dautilpy-0.2.0.dist-info/RECORD
